vdtoys/ansi.py
vdtoys/cache.py
vdtoys/framing.py
vdtoys/localstorage.py
vdtoys/mvc.py
vdtoys/plot.py
vdtoys/registry.py
vdtoys-0.1.7.dist-info/METADATA
vdtoys-0.1.7.dist-info/WHEEL
vdtoys-0.1.7.dist-info/RECORD
