Metadata-Version: 2.4
Name: vdtoys
Version: 0.1.7
Summary: visualdust's useless utils
Author: VisualDust
Author-email: gavin@gong.host
Requires-Python: >=3.10,<4.0
Classifier: Programming Language :: Python :: 3
Classifier: Programming Language :: Python :: 3.10
Classifier: Programming Language :: Python :: 3.11
Classifier: Programming Language :: Python :: 3.12
Classifier: Programming Language :: Python :: 3.13
Classifier: Programming Language :: Python :: 3.14
Requires-Dist: loguru (>=0.7.3)
